odoo8_addon_web_dashboard_open_action-8.0.1.0.0-py2.7-nspkg.pth
odoo_addons/web_dashboard_open_action/__openerp__.py
odoo_addons/web_dashboard_open_action/__init__.py
odoo_addons/web_dashboard_open_action/README.rst
odoo_addons/web_dashboard_open_action/views/templates.xml
odoo_addons/web_dashboard_open_action/static/description/icon.png
odoo_addons/web_dashboard_open_action/static/src/js/web_dashboard_open_action.js
odoo_addons/web_dashboard_open_action/static/src/css/web_dashboard_open_action.css
odoo_addons/web_dashboard_open_action/static/src/xml/web_dashboard_open_action.xml
odoo8_addon_web_dashboard_open_action-8.0.1.0.0.dist-info/top_level.txt
odoo8_addon_web_dashboard_open_action-8.0.1.0.0.dist-info/WHEEL
odoo8_addon_web_dashboard_open_action-8.0.1.0.0.dist-info/RECORD
odoo8_addon_web_dashboard_open_action-8.0.1.0.0.dist-info/metadata.json
odoo8_addon_web_dashboard_open_action-8.0.1.0.0.dist-info/DESCRIPTION.rst
odoo8_addon_web_dashboard_open_action-8.0.1.0.0.dist-info/METADATA
odoo8_addon_web_dashboard_open_action-8.0.1.0.0.dist-info/namespace_packages.txt
